LICENSE
README.md
setup.py
hf3fs_fuse/__init__.py
hf3fs_fuse/fuse.py
hf3fs_fuse/fuse_demo.py
hf3fs_fuse/io.py
hf3fs_py_usrbio.egg-info/PKG-INFO
hf3fs_py_usrbio.egg-info/SOURCES.txt
hf3fs_py_usrbio.egg-info/dependency_links.txt
hf3fs_py_usrbio.egg-info/not-zip-safe
hf3fs_py_usrbio.egg-info/requires.txt
hf3fs_py_usrbio.egg-info/top_level.txt